Metadata-Version: 2.1
Name: prefai
Version: 0.0.4
Summary: A brief description of your package
Home-page: http://github.com/prefai/pythonclient
Author: Bobby Jaros
Author-email: bobby@pref.ai
License: LICENSE.txt
Classifier: Programming Language :: Python
Classifier: Programming Language :: Python :: 3
Classifier: Programming Language :: Python :: 3.8
Requires-Python: >=3.6
License-File: LICENSE.txt
